jack-audio/__init__.py
jackAudio/__init__.py
jackAudio-1.0.3.dist-info/LICENSE
jackAudio-1.0.3.dist-info/METADATA
jackAudio-1.0.3.dist-info/WHEEL
jackAudio-1.0.3.dist-info/top_level.txt
jackAudio-1.0.3.dist-info/RECORD
